{"data":{"user":{"name":"Carlos Larriu","bio":"Hello world","avatarUrl":"https://avatars.githubusercontent.com/u/34486546?u=5e8b185eea6f61c1ab937dac42378318378bfdaa&v=4","location":null,"pinnedItems":{"totalCount":6,"edges":[{"node":{"name":"GPRS_P3_2","description":"Second part of the third practical project: Complex simulator of a video provider CPD","forkCount":0,"stargazers":{"totalCount":0},"url":"https://github.com/clarriu97/GPRS_P3_2","id":"MDEwOlJlcG9zaXRvcnkzMDg2OTg0OTg=","diskUsage":58,"primaryLanguage":{"name":"Java","color":"#b07219"}}},{"node":{"name":"CLACChat","description":"Android app based in a chat for DSCR subject in the university","forkCount":0,"stargazers":{"totalCount":0},"url":"https://github.com/clarriu97/CLACChat","id":"MDEwOlJlcG9zaXRvcnkyOTk1NDIyNTA=","diskUsage":1155,"primaryLanguage":{"name":"Java","color":"#b07219"}}},{"node":{"name":"FirebaseTutorial","description":null,"forkCount":0,"stargazers":{"totalCount":0},"url":"https://github.com/clarriu97/FirebaseTutorial","id":"MDEwOlJlcG9zaXRvcnkyODk1MTMwODU=","diskUsage":178,"primaryLanguage":{"name":"Java","color":"#b07219"}}},{"node":{"name":"in3model","description":null,"forkCount":0,"stargazers":{"totalCount":0},"url":"https://github.com/clarriu97/in3model","id":"MDEwOlJlcG9zaXRvcnkyOTUxMzc4MTY=","diskUsage":385,"primaryLanguage":{"name":"Java","color":"#b07219"}}},{"node":{"name":"MandelbrotGame","description":null,"forkCount":0,"stargazers":{"totalCount":0},"url":"https://github.com/clarriu97/MandelbrotGame","id":"MDEwOlJlcG9zaXRvcnkyOTk1NDUxMjE=","diskUsage":131,"primaryLanguage":{"name":"Java","color":"#b07219"}}},{"node":{"name":"ShipWar","description":"Version of the popular game Ship War (Guerra de Naves)","forkCount":0,"stargazers":{"totalCount":0},"url":"https://github.com/clarriu97/ShipWar","id":"MDEwOlJlcG9zaXRvcnkyOTk1NDk3ODg=","diskUsage":605,"primaryLanguage":{"name":"Java","color":"#b07219"}}}]}}}}